<?xml version="1.0" encoding="utf-8"?>
<TaskPackage>
	<finalTaskPosition>0</finalTaskPosition>
  <tasks>
  	<NewTask executionTime = "1">
  		<dependencyPositions>
  			<int>1</int>
  			<int>2</int>
  			<int>3</int>
  		</dependencyPositions>
  	</NewTask>
  	<NewTask executionTime = "2">
  		<dependencyPositions>
  			<int>4</int>
  		</dependencyPositions>
  	</NewTask>
  	<NewTask executionTime = "1">
  		<dependencyPositions>
  			<int>4</int>
  		</dependencyPositions>
  	</NewTask>
  	<NewTask executionTime = "1">
  		<dependencyPositions>
  			<int>4</int>
  		</dependencyPositions>
  	</NewTask>
  	<NewTask executionTime = "1">
  		<dependencyPositions>
  		</dependencyPositions>SomeModel>
  <SomeStringElementName>testData</SomeStringElementName>
  <SomeInfoElementName>5</SomeInfoElementName>
</SomeModel>
  	</NewTask>
  </tasks>
</TaskPackage>